focuscreen/__init__.py
focuscreen/app.py
focuscreen/cursor_renderer.py
focuscreen/focus_region_updater.py
focuscreen-0.8.dist-info/METADATA
focuscreen-0.8.dist-info/WHEEL
focuscreen-0.8.dist-info/top_level.txt
focuscreen-0.8.dist-info/RECORD
