Metadata-Version: 2.1
Name: focuscreen
Version: 0.8
Summary: Snap screen by focusing on mouse and keyboard events
Author: Hansimov
Project-URL: Homepage, https://github.com/Hansimov/focuscreen
Project-URL: Issues, https://github.com/Hansimov/focuscreen/issues
Classifier: Programming Language :: Python :: 3
Classifier: License :: OSI Approved :: MIT License
Classifier: Operating System :: OS Independent
Requires-Python: >=3.6
Requires-Dist: mss
Requires-Dist: numpy
Requires-Dist: opencv-python
Requires-Dist: Pillow
Requires-Dist: pynput
Requires-Dist: tclogger
